farsitools/PersianTools.py
farsitools/__init__.py
farsitools-1.1.dist-info/METADATA
farsitools-1.1.dist-info/WHEEL
farsitools-1.1.dist-info/top_level.txt
farsitools-1.1.dist-info/RECORD
